invoicetronic_sdk/__init__.py
invoicetronic_sdk/api_client.py
invoicetronic_sdk/api_response.py
invoicetronic_sdk/configuration.py
invoicetronic_sdk/exceptions.py
invoicetronic_sdk/py.typed
invoicetronic_sdk/rest.py
invoicetronic_sdk/api/__init__.py
invoicetronic_sdk/api/company_api.py
invoicetronic_sdk/api/log_api.py
invoicetronic_sdk/api/receive_api.py
invoicetronic_sdk/api/send_api.py
invoicetronic_sdk/api/status_api.py
invoicetronic_sdk/api/update_api.py
invoicetronic_sdk/api/webhook_api.py
invoicetronic_sdk/models/__init__.py
invoicetronic_sdk/models/allegati.py
invoicetronic_sdk/models/altri_dati_gestionali.py
invoicetronic_sdk/models/anagrafica.py
invoicetronic_sdk/models/cedente_prestatore.py
invoicetronic_sdk/models/cessionario_committente.py
invoicetronic_sdk/models/codice_articolo.py
invoicetronic_sdk/models/company.py
invoicetronic_sdk/models/contatti.py
invoicetronic_sdk/models/contatti_trasmittente.py
invoicetronic_sdk/models/dati_anagrafici.py
invoicetronic_sdk/models/dati_anagrafici_cedente_prestatore.py
invoicetronic_sdk/models/dati_anagrafici_cessionario_committente.py
invoicetronic_sdk/models/dati_anagrafici_vettore.py
invoicetronic_sdk/models/dati_beni_servizi.py
invoicetronic_sdk/models/dati_bollo.py
invoicetronic_sdk/models/dati_cassa_previdenziale.py
invoicetronic_sdk/models/dati_contratto.py
invoicetronic_sdk/models/dati_convenzione.py
invoicetronic_sdk/models/dati_ddt.py
invoicetronic_sdk/models/dati_fatture_collegate.py
invoicetronic_sdk/models/dati_generali.py
invoicetronic_sdk/models/dati_generali_documento.py
invoicetronic_sdk/models/dati_ordine_acquisto.py
invoicetronic_sdk/models/dati_pagamento.py
invoicetronic_sdk/models/dati_ricezione.py
invoicetronic_sdk/models/dati_riepilogo.py
invoicetronic_sdk/models/dati_ritenuta.py
invoicetronic_sdk/models/dati_sal.py
invoicetronic_sdk/models/dati_trasmissione.py
invoicetronic_sdk/models/dati_trasporto.py
invoicetronic_sdk/models/dati_veicoli.py
invoicetronic_sdk/models/dettaglio_linee.py
invoicetronic_sdk-1.1.7.dist-info/licenses/LICENSE
invoicetronic_sdk-1.1.7.dist-info/METADATA
invoicetronic_sdk-1.1.7.dist-info/WHEEL
invoicetronic_sdk-1.1.7.dist-info/top_level.txt
invoicetronic_sdk-1.1.7.dist-info/RECORD
