Metadata-Version: 2.4
Name: invoicetronic_sdk
Version: 1.1.7
Summary: Invoicetronic API
Home-page: https://invoicetronic.com
Author: Invoicetronic
Author-email: Invoicetronic <info@invoicetronic.com>
License: MIT
Project-URL: Repository, https://github.com/invoicetronic/python-sdk
Keywords: OpenAPI,OpenAPI-Generator,Invoicetronic API
Requires-Python: >=3.9
License-File: LICENSE
Requires-Dist: urllib3<3.0.0,>=2.1.0
Requires-Dist: python-dateutil>=2.8.2
Requires-Dist: pydantic>=2
Requires-Dist: typing-extensions>=4.7.1
Dynamic: author
Dynamic: home-page
Dynamic: license-file
